django_templatetags_ext/__init__.py
django_templatetags_ext/templatetags/__init__.py
django_templatetags_ext/templatetags/templatehelper.py
django_templatetags_ext-1.0.3.dist-info/METADATA
django_templatetags_ext-1.0.3.dist-info/WHEEL
django_templatetags_ext-1.0.3.dist-info/top_level.txt
django_templatetags_ext-1.0.3.dist-info/RECORD
