Metadata-Version: 2.1
Name: django-templatetags-ext
Version: 1.0.3
Summary: Django TemplateTags Extensions
Home-page: https://github.com/django-xxx/django-templatetags-extensions
Author: Hackathon
Author-email: kimi.huang@brightcells.com
Keywords: Django Template Tags TemplateTags Ext Extensions
Classifier: Development Status :: 5 - Production/Stable
Classifier: Environment :: Web Environment
Classifier: Framework :: Django
Classifier: Intended Audience :: Developers
Classifier: Programming Language :: Python
Classifier: Topic :: Software Development :: Libraries :: Python Modules
Classifier: Topic :: Office/Business :: Financial :: Spreadsheet
Requires-Dist: django-six
Requires-Dist: monetary
Requires-Dist: screen
Requires-Dist: pysnippets
